autobahntestsuite/__init__.py
autobahntestsuite/_version.py
autobahntestsuite/broadcast.py
autobahntestsuite/caseset.py
autobahntestsuite/choosereactor.py
autobahntestsuite/echo.py
autobahntestsuite/fuzzing.py
autobahntestsuite/interfaces.py
autobahntestsuite/massconnect.py
autobahntestsuite/report.py
autobahntestsuite/rinterfaces.py
autobahntestsuite/serializer.py
autobahntestsuite/spectemplate.py
autobahntestsuite/testdb.py
autobahntestsuite/testee.py
autobahntestsuite/testrun.py
autobahntestsuite/util.py
autobahntestsuite/wampfuzzing.py
autobahntestsuite/wamptestee.py
autobahntestsuite/wamptestserver.py
autobahntestsuite/wsperfcontrol.py
autobahntestsuite/wsperfmaster.py
autobahntestsuite/wstest.py
autobahntestsuite/case/__init__.py
autobahntestsuite/case/case.py
autobahntestsuite/case/case10_1_1.py
autobahntestsuite/case/case12_x_x.py
autobahntestsuite/case/case1_1_1.py
autobahntestsuite/case/case1_1_2.py
autobahntestsuite/case/case1_1_3.py
autobahntestsuite/case/case1_1_4.py
autobahntestsuite/case/case1_1_5.py
autobahntestsuite/case/case1_1_6.py
autobahntestsuite/case/case1_1_7.py
autobahntestsuite/case/case1_1_8.py
autobahntestsuite/case/case1_2_1.py
autobahntestsuite/case/case1_2_2.py
autobahntestsuite/case/case1_2_3.py
autobahntestsuite/case/case1_2_4.py
autobahntestsuite/case/case1_2_5.py
autobahntestsuite/case/case1_2_6.py
autobahntestsuite/case/case1_2_7.py
autobahntestsuite/case/case1_2_8.py
autobahntestsuite/case/case2_1.py
autobahntestsuite/case/case2_10.py
autobahntestsuite/case/case2_11.py
autobahntestsuite/case/case2_2.py
autobahntestsuite/case/case2_3.py
autobahntestsuite/case/case2_4.py
autobahntestsuite/case/case2_5.py
autobahntestsuite/case/case2_6.py
autobahntestsuite/case/case2_7.py
autobahntestsuite/case/case2_8.py
autobahntestsuite/case/case2_9.py
autobahntestsuite/case/case3_1.py
autobahntestsuite/case/case3_2.py
autobahntestsuite/case/case3_3.py
autobahntestsuite/case/case3_4.py
autobahntestsuite/case/case3_5.py
autobahntestsuite-0.8.2.dist-info/METADATA
autobahntestsuite-0.8.2.dist-info/WHEEL
autobahntestsuite-0.8.2.dist-info/entry_points.txt
autobahntestsuite-0.8.2.dist-info/top_level.txt
autobahntestsuite-0.8.2.dist-info/RECORD
