Metadata-Version: 2.1
Name: autobahntestsuite
Version: 0.8.2
Summary: AutobahnTestSuite - WebSocket/WAMP protocol implementation test suite.
Home-page: http://autobahn.ws/testsuite
Author: Crossbar.io Technologies GmbH
Author-email: autobahnws@googlegroups.com
License: Apache License 2.0
Keywords: autobahn autobahn.ws websocket wamp realtime test testsuite rfc6455 wstest wsperf
Platform: Any
Classifier: License :: OSI Approved :: Apache Software License
Classifier: Development Status :: 5 - Production/Stable
Classifier: Environment :: Console
Classifier: Framework :: Twisted
Classifier: Intended Audience :: Developers
Classifier: Operating System :: OS Independent
Classifier: Programming Language :: Python
Classifier: Topic :: Internet
Classifier: Topic :: Software Development :: Testing
Requires-Dist: setuptools
Requires-Dist: txaio (<=2.1.0)
Requires-Dist: autobahn[accelerate,twisted] (==0.10.9)
Requires-Dist: jinja2 (>=2.6)
Requires-Dist: markupsafe (>=0.19)
Requires-Dist: Werkzeug (>=0.9.4)
Requires-Dist: klein (>=0.2.1)
Requires-Dist: pyopenssl (>=0.14)
Requires-Dist: service-identity (>=14.0.0)
Requires-Dist: unittest2 (>=1.1.0)
